argspec/__init__.py
argspec/argspec.py
argspec/errors.py
argspec/metadata.py
argspec/parse.py
argspec/py.typed
argspec/readenv.py
argspec-0.4.1.dist-info/METADATA
argspec-0.4.1.dist-info/WHEEL
argspec-0.4.1.dist-info/licenses/LICENSE
argspec-0.4.1.dist-info/RECORD
