Metadata-Version: 2.4
Name: argspec
Version: 0.4.1
Summary: A library for cleanly and succinctly performing type-safe command-line argument parsing via a declarative interface.
Project-URL: repository, https://github.com/lilellia/argspec
Project-URL: Bug Tracker, https://github.com/lilellia/argspec/issues
Author-email: Lily Ellington <lilell_@outlook.com>
License-File: LICENSE
Keywords: argparse,argument-parser,argument-parsing,arguments,cli,command-line,type-safe
Classifier: Development Status :: 4 - Beta
Classifier: Intended Audience :: Developers
Classifier: License :: OSI Approved :: MIT License
Classifier: Operating System :: OS Independent
Classifier: Programming Language :: Python
Classifier: Programming Language :: Python :: 3
Classifier: Programming Language :: Python :: 3.10
Classifier: Programming Language :: Python :: 3.11
Classifier: Programming Language :: Python :: 3.12
Classifier: Programming Language :: Python :: 3.13
Classifier: Programming Language :: Python :: 3.14
Classifier: Topic :: Software Development :: Libraries
Classifier: Topic :: Software Development :: Libraries :: Python Modules
Classifier: Topic :: Utilities
Requires-Python: >=3.10
Requires-Dist: typewire>=1.3.0
Requires-Dist: typing-extensions>=4.15.0
